datakit_local/__init__.py
datakit_local/cli.py
datakit_local/server.py
datakit_local/static/datakit.png
datakit_local/static/index.html
datakit_local/static/assets/csv-CoenXKpC.png
datakit_local/static/assets/duckdb-BOTUCxRM.js
datakit_local/static/assets/index-Cz5ez0nn.js
datakit_local/static/assets/index-D_WKf_BU.css
datakit_local/static/assets/json-CjjK0oAt.png
datakit_local/static/assets/parquet-SdsFHa0D.png
datakit_local/static/assets/xlsx-DkH2s96g.js
datakit_local/static/assets/xlsx-VMtgsrbP.png
datakit_local-0.1.31.dist-info/licenses/LICENSE
datakit_local-0.1.31.dist-info/METADATA
datakit_local-0.1.31.dist-info/WHEEL
datakit_local-0.1.31.dist-info/entry_points.txt
datakit_local-0.1.31.dist-info/top_level.txt
datakit_local-0.1.31.dist-info/RECORD
