Metadata-Version: 2.4
Name: datakit-local
Version: 0.1.31
Summary: Modern web-based data analysis tool - process CSV/JSON/EXCEL/PARQUET files locally with SQL
Home-page: https://datakit.page
Author: DataKit Team
Author-email: amin@wavequery.com
Project-URL: Homepage, https://datakit.page
Project-URL: Documentation, https://docs.datakit.page
Project-URL: Bug Reports, https://docs.datakit.page
Keywords: data-analysis,csv,json,sql,duckdb,local,privacy,analytics,visualization
Classifier: Development Status :: 4 - Beta
Classifier: Intended Audience :: Developers
Classifier: Intended Audience :: Science/Research
Classifier: License :: OSI Approved :: MIT License
Classifier: Operating System :: OS Independent
Classifier: Programming Language :: Python :: 3
Classifier: Programming Language :: Python :: 3.8
Classifier: Programming Language :: Python :: 3.9
Classifier: Programming Language :: Python :: 3.10
Classifier: Programming Language :: Python :: 3.11
Classifier: Programming Language :: Python :: 3.12
Classifier: Topic :: Scientific/Engineering :: Information Analysis
Classifier: Topic :: Database
Classifier: Topic :: Internet :: WWW/HTTP :: HTTP Servers
Classifier: Topic :: Software Development :: User Interfaces
Requires-Python: >=3.8
License-File: LICENSE
Requires-Dist: click>=8.0.0
Requires-Dist: uvicorn>=0.18.0
Requires-Dist: fastapi>=0.68.0
Requires-Dist: aiofiles>=0.8.0
Provides-Extra: dev
Requires-Dist: pytest>=6.0; extra == "dev"
Requires-Dist: pytest-asyncio; extra == "dev"
Requires-Dist: black; extra == "dev"
Requires-Dist: isort; extra == "dev"
Requires-Dist: flake8; extra == "dev"
Dynamic: author
Dynamic: author-email
Dynamic: classifier
Dynamic: description
Dynamic: description-content-type
Dynamic: home-page
Dynamic: keywords
Dynamic: license-file
Dynamic: project-url
Dynamic: provides-extra
Dynamic: requires-dist
Dynamic: requires-python
Dynamic: summary
